mypackage/__init__.py
mypackage/mymodule.py
tests/__init__.py
tests/test_mymodule.py
buff_package-0.0.3.dist-info/LICENSE
buff_package-0.0.3.dist-info/METADATA
buff_package-0.0.3.dist-info/WHEEL
buff_package-0.0.3.dist-info/top_level.txt
buff_package-0.0.3.dist-info/RECORD
