Metadata-Version: 2.1
Name: buff-package
Version: 0.0.3
Summary: Practice Package
Home-page: https://github.com/buff91/python-practice
Author: buff
Author-email: buff@kakao.com
Classifier: Programming Language :: Python :: 3
Classifier: License :: OSI Approved :: MIT License
Classifier: Operating System :: OS Independent
Requires-Python: >=3.10
License-File: LICENSE
